mcp_korea_tourism-0.1.1.dist-info/licenses/LICENSE
mcp_tourism/__init__.py
mcp_tourism/api_client.py
mcp_tourism/server.py
mcp_korea_tourism-0.1.1.dist-info/METADATA
mcp_korea_tourism-0.1.1.dist-info/WHEEL
mcp_korea_tourism-0.1.1.dist-info/top_level.txt
mcp_korea_tourism-0.1.1.dist-info/RECORD
