Metadata-Version: 2.4
Name: mcp-korea-tourism
Version: 0.1.1
Summary: MCP Server for Korea Tourism API
Author-email: Harim Kang <harimkang4422@gmail.com>
License-Expression: MIT
Project-URL: Repository, https://github.com/harimkang/mcp-korea-tourism-api
Classifier: Development Status :: 4 - Beta
Classifier: Intended Audience :: Developers
Classifier: Programming Language :: Python :: 3
Classifier: Programming Language :: Python :: 3.10
Classifier: Programming Language :: Python :: 3.11
Classifier: Programming Language :: Python :: 3.12
Classifier: Operating System :: OS Independent
Classifier: Topic :: Software Development :: Libraries :: Application Frameworks
Requires-Python: >=3.12
License-File: LICENSE
Requires-Dist: cachetools>=5.5.2
Requires-Dist: httpx>=0.28.1
Requires-Dist: mcp[cli]>=1.6.0
Requires-Dist: ratelimit>=2.2.1
Requires-Dist: tenacity>=9.1.2
Dynamic: license-file
